psrm/__init__.py
psrm/__main__.py
psrm/monitor.py
psrm/py.typed
psrm/utils.py
psrm-0.1.3.dist-info/WHEEL
psrm-0.1.3.dist-info/entry_points.txt
psrm-0.1.3.dist-info/METADATA
psrm-0.1.3.dist-info/RECORD
