Metadata-Version: 2.3
Name: psrm
Version: 0.1.3
Summary: A process system resource usage monitor.
Author: Ray
Author-email: Ray <smallzhu66@163.com>
Requires-Dist: matplotlib>=3.10.8
Requires-Dist: psutil>=7.1.3
Requires-Dist: pydantic-settings>=2.12.0
Requires-Python: >=3.10
